{
  "template": "https://github.com/robert-koch-institut/mex-template",
  "commit": "71224cdf6b9828906fd1591f7572bdb12f8f9408",
  "checkout": null,
  "context": {
    "cookiecutter": {
      "project_name": "artificial",
      "short_summary": "Create artificial data for the MEx project.",
      "long_summary": "Create artificial extracted items, transform them into merged items and write the results into a configured sink.",
      "_template": "https://github.com/robert-koch-institut/mex-template",
      "_commit": "71224cdf6b9828906fd1591f7572bdb12f8f9408"
    }
  },
  "directory": null
}
